violetbeacon_deptrack_client/__init__.py
violetbeacon_deptrack_client/cli.py
violetbeacon_deptrack_client/config.py
violetbeacon_deptrack_client/params.py
violetbeacon_deptrack_client/cli_command/__init__.py
violetbeacon_deptrack_client/cli_command/create_config.py
violetbeacon_deptrack_client/cli_command/upload_bom.py
violetbeacon_deptrack_client/cli_command/version.py
violetbeacon_deptrack_client/dependency_track/api.py
violetbeacon_deptrack_client-0.1.1.dist-info/licenses/LICENSE.md
violetbeacon_deptrack_client-0.1.1.dist-info/METADATA
violetbeacon_deptrack_client-0.1.1.dist-info/WHEEL
violetbeacon_deptrack_client-0.1.1.dist-info/entry_points.txt
violetbeacon_deptrack_client-0.1.1.dist-info/top_level.txt
violetbeacon_deptrack_client-0.1.1.dist-info/RECORD
