Metadata-Version: 2.4
Name: violetbeacon-deptrack-client
Version: 0.1.1
Summary: Dependency-Track client by VioletBeacon
Author-email: Kris Hardy <kris.hardy@vltbcn.com>
License-Expression: GPL-3.0-or-later
Project-URL: Homepage, https://github.com/VioletBeacon/deptrack-client
Project-URL: Issues, https://github.com/VioletBeacon/deptrack-client/issues
Keywords: owasp,dependency-track
Classifier: Development Status :: 3 - Alpha
Classifier: Environment :: Console
Classifier: Intended Audience :: Developers
Classifier: Operating System :: POSIX
Classifier: Programming Language :: Python :: 3
Classifier: Topic :: Utilities
License-File: LICENSE.md
Requires-Dist: importlib
Requires-Dist: pydantic
Requires-Dist: requests
Requires-Dist: pyyaml
Dynamic: license-file
